geek_cafe_saas_models/_base_model.py
geek_cafe_saas_models/_base_tenant_model.py
geek_cafe_saas_models/_base_tenant_user_model.py
geek_cafe_saas_models/version.py
geek_cafe_saas_models/asset/README.md
geek_cafe_saas_models/asset/__init__.py
geek_cafe_saas_models/asset/asset_activity.py
geek_cafe_saas_models/asset/asset_assignment.py
geek_cafe_saas_models/asset/asset_file.py
geek_cafe_saas_models/asset/asset_security.py
geek_cafe_saas_models/asset/asset_tag.py
geek_cafe_saas_models/asset/asset_tree_node.py
geek_cafe_saas_models/asset/asset_trigger.py
geek_cafe_saas_models/asset/indexing/asset_indexes.py
geek_cafe_saas_models/asset/indexing/asset_tag_indexes.py
geek_cafe_saas_models/asset_managment/asset_security.py
geek_cafe_saas_models/assets/asset_security.py
geek_cafe_saas_models/contact/__init__.py
geek_cafe_saas_models/contact/campaign.py
geek_cafe_saas_models/contact/email.py
geek_cafe_saas_models/contact/interaction.py
geek_cafe_saas_models/contact/note.py
geek_cafe_saas_models/contact/pipeline.py
geek_cafe_saas_models/contact/tag.py
geek_cafe_saas_models/contact/task.py
geek_cafe_saas_models/content/_cms_base.py
geek_cafe_saas_models/content/content_block.py
geek_cafe_saas_models/content/enrollment.py
geek_cafe_saas_models/content/enrollment_indexes.py
geek_cafe_saas_models/content/page.py
geek_cafe_saas_models/content/page_indexes.py
geek_cafe_saas_models/content/site.py
geek_cafe_saas_models/content/template.py
geek_cafe_saas_models/core/activity/__init__.py
geek_cafe_saas_models/core/activity/indexing/activity_indexes.py
geek_cafe_saas_models/core/data_store/file.py
geek_cafe_saas_models/core/data_store/image.py
geek_cafe_saas_models/core/data_store/video.py
geek_cafe_saas_models/core/data_store/indexing/file_indexes.py
geek_cafe_saas_models/core/joins/relationship.py
geek_cafe_saas_models/core/joins/indexing/relationship_indexes.py
geek_cafe_saas_models/core/keywords/README.md
geek_cafe_saas_models/core/keywords/keyword.py
geek_cafe_saas_models-0.1.1.dist-info/METADATA
geek_cafe_saas_models-0.1.1.dist-info/WHEEL
geek_cafe_saas_models-0.1.1.dist-info/RECORD
