Metadata-Version: 2.4
Name: geek_cafe_saas_models
Version: 0.1.1
Summary: Geek Cafe SaaS Models
Author-email: Eric Wilson <eric.wilson@geekcafe.com>
Requires-Python: >=3.8
